fabfiles/__init__.py
fabfiles/fabfiles.py
fabfiles-0.1.0.dist-info/LICENSE
fabfiles-0.1.0.dist-info/METADATA
fabfiles-0.1.0.dist-info/WHEEL
fabfiles-0.1.0.dist-info/top_level.txt
fabfiles-0.1.0.dist-info/RECORD
