Metadata-Version: 2.1
Name: fabfiles
Version: 0.1.0
Summary: Reusable automation tasks and scripts based on fab-classic: cloud provisiotning, docker, etc.
Home-page: https://github.com/minireference/fabfiles
Author: Ivan Savov
Author-email: ivan@minireference.com
License: MIT license
Keywords: fabfiles
Platform: UNKNOWN
Classifier: Development Status :: 2 - Pre-Alpha
Classifier: Intended Audience :: Developers
Classifier: License :: OSI Approved :: MIT License
Classifier: Natural Language :: English
Classifier: Programming Language :: Python :: 3
Classifier: Programming Language :: Python :: 3.6
Classifier: Programming Language :: Python :: 3.7
Classifier: Programming Language :: Python :: 3.8
Requires-Python: >=3.6
License-File: LICENSE
Requires-Dist: fab-classic
